aprs/__init__.py
aprs/aprsis.py
aprs/base91.py
aprs/classes.py
aprs/constants.py
aprs/data_ext.py
aprs/decimaldegrees.py
aprs/geo_util.py
aprs/kiss.py
aprs/position.py
aprs/timestamp.py
aprs3-8.0.0.post1.dist-info/LICENSE
aprs3-8.0.0.post1.dist-info/METADATA
aprs3-8.0.0.post1.dist-info/WHEEL
aprs3-8.0.0.post1.dist-info/top_level.txt
aprs3-8.0.0.post1.dist-info/RECORD
