Metadata-Version: 2.1
Name: aprs3
Version: 8.0.0.post1
Summary: Python module for encoding and decoding APRS data.
Author-email: Masen Furer KF7HVM <kf7hvm@0x26.net>, Greg Albrecht W2GMD <oss@undef.net>
License: Copyright 2017 Greg Albrecht and Contributors        
Project-URL: Homepage, https://github.com/python-aprs/aprs3
Keywords: Ham Radio,APRS,KISS
Classifier: License :: OSI Approved :: Apache Software License
Classifier: Topic :: Communications :: Ham Radio
Classifier: Programming Language :: Python
Classifier: License :: OSI Approved :: Apache Software License
License-File: LICENSE
Requires-Dist: attrs (>20)
Requires-Dist: ax253 (>=0.1.5)
Requires-Dist: kiss3 (>=8.0.0)
